LICENSE
README.md
setup.py
dbconsmart/__init__.py
dbconsmart.egg-info/PKG-INFO
dbconsmart.egg-info/SOURCES.txt
dbconsmart.egg-info/dependency_links.txt
dbconsmart.egg-info/entry_points.txt
dbconsmart.egg-info/top_level.txt
dbconsmart/mongo/__init__.py
dbconsmart/mongo/crud.py